Workbook

Sheet Assumptions
A1: FINANCIAL IMPACT MODEL – ASSUMPTIONS (Illustrative)
A3: Assumption | B3: Value | C3: Unit | D3: Notes
A4: Number of Rooms | B4: 250 | C4: rooms | D4: Illustrative portfolio size
A5: Occupancy Rate | B5: 0.72 | C5: % | D5: Stabilized occupancy range
A6: ADR | B6: 450 | C6: AED | D6: Illustrative baseline ADR
A7: Days per Year | B7: 365 | C7: days | D7: Constant
A8: OTA Share | B8: 0.55 | C8: % | D8: Share of bookings via OTAs
A9: OTA Commission | B9: 0.2 | C9: % | D9: Commission range 15–25%
A10: Other Distribution Cost | B10: 0.02 | C10: % | D10: Payment/processing/other
A11: Operating Cost Rate | B11: 0.78 | C11: % | D11: As % of net revenue
A12: ADR Uplift +2% | B12: 0.02 | C12: % | D12: Sensitivity lever
A13: ADR Uplift +4% | B13: 0.04 | C13: % | D13: Sensitivity lever
A14: OTA Reduction (pp) | B14: 0.05 | C14: pp | D14: Reduce OTA share by 5pp
A15: Cost Efficiency | B15: 0.04 | C15: % | D15: Reduce operating cost rate by 4%

Sheet Base_Case
A1: BASE CASE – REVENUE, DISTRIBUTION COSTS & EBITDA
A3: Metric | B3: Formula | C3: Value | D3: Unit
A4: Available Room Nights | B4: =Assumptions!B4*Assumptions!B7 | C4: =B4 | D4: room-nights
A5: Room Nights Sold | B5: =Assumptions!B5*C4 | C5: =B5 | D5: room-nights
A6: Gross Room Revenue | B6: =Assumptions!B6*C5 | C6: =B6 | D6: AED
A7: OTA Commission Cost | B7: =Assumptions!B8*Assumptions!B9*C6 | C7: =B7 | D7: AED
A8: Other Distribution Costs | B8: =Assumptions!B10*C6 | C8: =B8 | D8: AED
A9: Net Revenue (after distribution) | B9: =C6-C7-C8 | C9: =B9 | D9: AED
A10: Operating Costs | B10: =Assumptions!B11*C9 | C10: =B10 | D10: AED
A11: EBITDA | B11: =C9-C10 | C11: =B11 | D11: AED
A12: EBITDA Margin | B12: =IF(C9=0,0,C11/C9) | C12: =B12 | D12: %

Sheet ADR_Sensitivity
A1: ADR SENSITIVITY – NET REVENUE & EBITDA IMPACT
A3: Scenario | B3: ADR (AED) | C3: Net Revenue (AED) | D3: EBITDA (AED) | E3: EBITDA Margin
A4: Base | B4: =Assumptions!B6 | C4: =(Base_Case!C5)*B4*(1-(Assumptions!B8)*(Assumptions!B9)-(Assumptions!B10)) | D4: =(Base_Case!C5)*B4*(1-(Assumptions!B8)*(Assumptions!B9)-(Assumptions!B10))*(1-(Assumptions!B11)) | E4: =IF(C4=0,0,D4/C4)
A5: +2% ADR | B5: =Assumptions!B6*(1+Assumptions!B12) | C5: =(Base_Case!C5)*B5*(1-(Assumptions!B8)*(Assumptions!B9)-(Assumptions!B10)) | D5: =(Base_Case!C5)*B5*(1-(Assumptions!B8)*(Assumptions!B9)-(Assumptions!B10))*(1-(Assumptions!B11)) | E5: =IF(C5=0,0,D5/C5)
A6: +4% ADR | B6: =Assumptions!B6*(1+Assumptions!B13) | C6: =(Base_Case!C5)*B6*(1-(Assumptions!B8)*(Assumptions!B9)-(Assumptions!B10)) | D6: =(Base_Case!C5)*B6*(1-(Assumptions!B8)*(Assumptions!B9)-(Assumptions!B10))*(1-(Assumptions!B11)) | E6: =IF(C6=0,0,D6/C6)

Sheet OTA_Shift_Model
A1: OTA SHARE SHIFT – NET REVENUE & EBITDA IMPACT
A3: Scenario | B3: OTA Share | C3: Net Revenue (AED) | D3: EBITDA (AED) | E3: EBITDA Margin
A4: Base | B4: =Assumptions!B8 | C4: =(Base_Case!C5)*(Assumptions!B6)*(1-(B4)*(Assumptions!B9)-(Assumptions!B10)) | D4: =(Base_Case!C5)*(Assumptions!B6)*(1-(B4)*(Assumptions!B9)-(Assumptions!B10))*(1-(Assumptions!B11)) | E4: =IF(C4=0,0,D4/C4)
A5: -5pp OTA share | B5: =MAX(0,Assumptions!B8-Assumptions!B14) | C5: =(Base_Case!C5)*(Assumptions!B6)*(1-(B5)*(Assumptions!B9)-(Assumptions!B10)) | D5: =(Base_Case!C5)*(Assumptions!B6)*(1-(B5)*(Assumptions!B9)-(Assumptions!B10))*(1-(Assumptions!B11)) | E5: =IF(C5=0,0,D5/C5)

Sheet Scenario_Output
A1: SCENARIO OUTPUT – BASE VS OPTIMISTIC VS RISK
A3: Metric | B3: Base | C3: Optimistic | D3: Risk
A4: Net Revenue (AED) | B4: =(Base_Case!C5)*(Assumptions!B6)*(1-(Assumptions!B8)*(Assumptions!B9)-(Assumptions!B10)) | C4: =(Base_Case!C5)*(Assumptions!B6*(1+Assumptions!B12))*(1-(MAX(0,Assumptions!B8-Assumptions!B14))*(Assumptions!B9)-(Assumptions!B10)) | D4: =(Base_Case!C5)*(Assumptions!B6*(1-Assumptions!B12))*(1-(MIN(1,Assumptions!B8+Assumptions!B14))*(Assumptions!B9)-(Assumptions!B10))
A5: EBITDA (AED) | B5: =(Base_Case!C5)*(Assumptions!B6)*(1-(Assumptions!B8)*(Assumptions!B9)-(Assumptions!B10))*(1-(Assumptions!B11)) | C5: =(Base_Case!C5)*(Assumptions!B6*(1+Assumptions!B12))*(1-(MAX(0,Assumptions!B8-Assumptions!B14))*(Assumptions!B9)-(Assumptions!B10))*(1-(MAX(0,Assumptions!B11*(1-Assumptions!B15)))) | D5: =(Base_Case!C5)*(Assumptions!B6*(1-Assumptions!B12))*(1-(MIN(1,Assumptions!B8+Assumptions!B14))*(Assumptions!B9)-(Assumptions!B10))*(1-(MIN(1,Assumptions!B11*(1+0.03))))
A6: EBITDA Margin | B6: =IF(B4=0,0,B5/B4) | C6: =IF(C4=0,0,C5/C4) | D6: =IF(D4=0,0,D5/D4)
A8: Notes
A9: Optimistic: ADR +2%, OTA share -5pp, operating cost rate reduced by 4% efficiency.
A10: Risk: ADR -2%, OTA share +5pp, operating cost rate increased by 3% inflation.
